bamboo4py/__init__.py
bamboo4py/__main__.py
bamboo4py/deployment.py
bamboo4py/drivers/__init__.py
bamboo4py/drivers/change_actions.py
bamboo4py/drivers/mock.py
bamboo4py/drivers/net.py
bamboo4py/drivers/podman.py
bamboo4py/drivers/protocol.py
bamboo4py/tyaml.py
bamboo4py-0.1.2.dist-info/entry_points.txt
bamboo4py-0.1.2.dist-info/LICENSE
bamboo4py-0.1.2.dist-info/WHEEL
bamboo4py-0.1.2.dist-info/METADATA
bamboo4py-0.1.2.dist-info/RECORD
